README.md
setup.py
recommendation_system/__init__.py
recommendation_system/recommendation_system.py
recommendation_system.egg-info/PKG-INFO
recommendation_system.egg-info/SOURCES.txt
recommendation_system.egg-info/dependency_links.txt
recommendation_system.egg-info/requires.txt
recommendation_system.egg-info/top_level.txt