Metadata-Version: 1.0
Name: recommendation-system
Version: 1.0.0
Summary: Simple Recommendation System in Python3+ (Using Collaborative Filtering)
Home-page: https://github.com/CodingVanGogh/Recommendation-System
Author: Coding Van Gogh
Author-email: UNKNOWN
License: MIT
Keywords: Recommendation System Movie recommender collaborative filtering low rank matrix factorization
Platform: UNKNOWN
